{
  "name": "React Hookers",
  "includeVersion": true,
  "excludePrivate": true,
  "excludeExternals": true,
  "excludeInternal": true,
  "disableSources": true,
  "hideGenerator": true,
  "readme": "none",
  "tsconfig": "./tsconfig.json",
  "customCss": "./node_modules/typedoc-custom-css/custom.css",
  "entryPoints": [
    "./src/main/index.ts"
  ],
  "externalSymbolLinkMappings": {
    "global": {
      "AbortSignal": "https://developer.mozilla.org/en-US/docs/Web/API/AbortController",
      "Promise": "https://developer.mozilla.org/en-US/docs/Web/JavaScript/Reference/Global_Objects/Promise"
    },
    "typescript": {
      "AbortSignal": "https://developer.mozilla.org/en-US/docs/Web/API/AbortController",
      "Promise": "https://developer.mozilla.org/en-US/docs/Web/JavaScript/Reference/Global_Objects/Promise"
    }
  }
}
